PipeGraphPy/__init__.py
PipeGraphPy/common.py
PipeGraphPy/constants.py
PipeGraphPy/decorators.py
PipeGraphPy/logger.py
PipeGraphPy/tools.py
PipeGraphPy/config/__init__.py
PipeGraphPy/config/custom.py
PipeGraphPy/config/default_settings.py
PipeGraphPy/core/__init__.py
PipeGraphPy/core/anchor.cpython-310-x86_64-linux-gnu.so
PipeGraphPy/core/edge.cpython-310-x86_64-linux-gnu.so
PipeGraphPy/core/graph.cpython-310-x86_64-linux-gnu.so
PipeGraphPy/core/graph_base.cpython-310-x86_64-linux-gnu.so
PipeGraphPy/core/module.cpython-310-x86_64-linux-gnu.so
PipeGraphPy/core/node.cpython-310-x86_64-linux-gnu.so
PipeGraphPy/core/pipegraph.cpython-310-x86_64-linux-gnu.so
PipeGraphPy/core/modcls/__init__.py
PipeGraphPy/core/modcls/base.cpython-310-x86_64-linux-gnu.so
PipeGraphPy/core/modcls/branchselect.cpython-310-x86_64-linux-gnu.so
PipeGraphPy/core/modcls/classifier.cpython-310-x86_64-linux-gnu.so
PipeGraphPy/core/modcls/cluster.cpython-310-x86_64-linux-gnu.so
PipeGraphPy/core/modcls/datacharts.cpython-310-x86_64-linux-gnu.so
PipeGraphPy/core/modcls/deeplearning.cpython-310-x86_64-linux-gnu.so
PipeGraphPy/core/modcls/endscript.cpython-310-x86_64-linux-gnu.so
PipeGraphPy/core/modcls/ensemble.cpython-310-x86_64-linux-gnu.so
PipeGraphPy/core/modcls/evaluate.cpython-310-x86_64-linux-gnu.so
PipeGraphPy/core/modcls/exportdata.cpython-310-x86_64-linux-gnu.so
PipeGraphPy/core/modcls/handlescript.cpython-310-x86_64-linux-gnu.so
PipeGraphPy/core/modcls/importdata.cpython-310-x86_64-linux-gnu.so
PipeGraphPy/core/modcls/merge.cpython-310-x86_64-linux-gnu.so
PipeGraphPy/core/modcls/mergescript.cpython-310-x86_64-linux-gnu.so
PipeGraphPy/core/modcls/metrics.cpython-310-x86_64-linux-gnu.so
PipeGraphPy/core/modcls/postprocessor.cpython-310-x86_64-linux-gnu.so
PipeGraphPy/core/modcls/preprocessor.cpython-310-x86_64-linux-gnu.so
PipeGraphPy/core/modcls/pythonscript.cpython-310-x86_64-linux-gnu.so
PipeGraphPy/core/modcls/regressor.cpython-310-x86_64-linux-gnu.so
pipegraphpy-2.0.25.dist-info/METADATA
pipegraphpy-2.0.25.dist-info/WHEEL
pipegraphpy-2.0.25.dist-info/top_level.txt
pipegraphpy-2.0.25.dist-info/RECORD
