Metadata-Version: 2.4
Name: PipeGraphPy
Version: 2.0.25
Summary: 核心算法框架
Author: liujm
Author-email: 792079829@qq.com
License: Private
Classifier: Programming Language :: Python :: 3.9
Classifier: Programming Language :: Python :: 3.10
Classifier: Operating System :: POSIX :: Linux
Classifier: Operating System :: Microsoft :: Windows
Requires-Python: >=3.7
Requires-Dist: python-dateutil>=2.8.2
Requires-Dist: prettytable==3.7.0
Requires-Dist: pandas>=1.3.5
Requires-Dist: joblib>=1.3.2
Requires-Dist: dbpoolpy>=0.6.11
Dynamic: classifier
Dynamic: license
Dynamic: requires-dist
Dynamic: summary
